seedee/seedee_wrapper.cpython-310-x86_64-linux-gnu.so
seedee/seedee_wrapper.pyx
seedee/seedee_wrapper.pxd
seedee/__init__.py
seedee-0.3.1.dist-info/RECORD
seedee-0.3.1.dist-info/top_level.txt
seedee-0.3.1.dist-info/LICENSE_THIRDPARTY.txt
seedee-0.3.1.dist-info/METADATA
seedee-0.3.1.dist-info/LICENSE
seedee-0.3.1.dist-info/WHEEL
seedee.libs/libseedee-786ce599.so.0.3.1
