Metadata-Version: 2.1
Name: seedee
Version: 0.3.1
Summary: A (de)serialization library for multidimensional arrays
Home-page: https://gitlab.desy.de/fs-sc/seedee
Author: Tim Schoof
Author-email: tim.schoof@desy.de
License: MIT
Classifier: License :: OSI Approved :: MIT License
Classifier: Programming Language :: Python
Classifier: Programming Language :: Python :: 3
Classifier: Programming Language :: Python :: 3.6
Classifier: Programming Language :: Python :: 3.7
Classifier: Programming Language :: Python :: 3.8
Classifier: Programming Language :: Python :: 3.9
Classifier: Programming Language :: Python :: 3.10
Classifier: Programming Language :: Python :: 3.11
Classifier: Programming Language :: Python :: 3.12
Classifier: Programming Language :: Python :: Implementation :: CPython
Classifier: Development Status :: 4 - Beta
Requires-Python: >=3.6
License-File: LICENSE
License-File: LICENSE_THIRDPARTY.txt
Requires-Dist: numpy
Provides-Extra: tests
Requires-Dist: pytest ; extra == 'tests'
Requires-Dist: h5py ; extra == 'tests'
Requires-Dist: hdf5plugin ; extra == 'tests'
